vissuAlize/__init__.py
vissuAlize/main.py
vissuAlize-0.1.1.dist-info/LICENSE
vissuAlize-0.1.1.dist-info/METADATA
vissuAlize-0.1.1.dist-info/WHEEL
vissuAlize-0.1.1.dist-info/top_level.txt
vissuAlize-0.1.1.dist-info/RECORD
