Metadata-Version: 2.1
Name: vissuAlize
Version: 0.1.1
Summary: High-level visualization library built on top of matplotlib and seaborn
Home-page: https://github.com/hocuf/vissuAlize
Author: Abdullah Fatih Höcü
Author-email: abdullahhocu19@hotmail.com
License: UNKNOWN
Platform: UNKNOWN
Classifier: Development Status :: 3 - Alpha
Classifier: Intended Audience :: Developers
Classifier: Natural Language :: English
Classifier: Programming Language :: Python :: 3
Classifier: License :: OSI Approved :: MIT License
License-File: LICENSE
Requires-Dist: matplotlib >=3.1.1
Requires-Dist: seaborn >=0.9.0
Requires-Dist: pandas >=0.25.0
